<?xml version="1.0" encoding="UTF-8"?>
<pevz:kontakte personid="10757" xmlns:pevz="http://ekvv.uni-bielefeld.de/pers_publ/">
    <pevz:kontakt id="10757">
        <pevz:einrichtung id="10040">
            <pevz:name>Technische Fakultät / AG Technische Informatik</pevz:name>
            <pevz:name_en>Faculty of Technology / AG Technische Informatik</pevz:name_en>
        </pevz:einrichtung>
        <pevz:funktion>Fremdsprachensekretärin</pevz:funktion>
        <pevz:email>angelika@ti.uni-bielefeld.de</pevz:email>
        <pevz:email_verschleiert>&amp;#97;ng&amp;#101;li&amp;#107;a@&amp;#116;i.&amp;#117;ni&amp;#45;bi&amp;#101;le&amp;#102;el&amp;#100;.d&amp;#101;</pevz:email_verschleiert>
        <pevz:url>http://www.ti.uni-bielefeld.de/html/people/angelika/</pevz:url>
        <pevz:telefon>6885</pevz:telefon>
        <pevz:fax>6440</pevz:fax>
        <pevz:telefon_sekretariat></pevz:telefon_sekretariat>
        <pevz:raum>UHG D4-152</pevz:raum>
        <pevz:sprechzeiten></pevz:sprechzeiten>
        <pevz:profs>nein</pevz:profs>
    </pevz:kontakt>
    <pevz:kontakt id="48291439">
        <pevz:einrichtung id="48167073">
            <pevz:name>Technische Fakultät / Int. Graduiertenkolleg DiDy (GRK 1906)</pevz:name>
            <pevz:name_en>Faculty of Technology / Int. Graduate Program DiDy (GRK 1906)</pevz:name_en>
        </pevz:einrichtung>
        <pevz:funktion>Sekretariat</pevz:funktion>
        <pevz:email></pevz:email>
        <pevz:email_verschleiert></pevz:email_verschleiert>
        <pevz:url></pevz:url>
        <pevz:telefon>3793</pevz:telefon>
        <pevz:fax></pevz:fax>
        <pevz:telefon_sekretariat></pevz:telefon_sekretariat>
        <pevz:raum>UHG U10-126</pevz:raum>
        <pevz:sprechzeiten>Mon: 14-17&#xd;
Wed, Fri: 10-13</pevz:sprechzeiten>
        <pevz:profs>nein</pevz:profs>
    </pevz:kontakt>
</pevz:kontakte>
