<?xml version="1.0" encoding="UTF-8"?>
<pevz:kontakte personid="8848385" xmlns:pevz="http://ekvv.uni-bielefeld.de/pers_publ/">
    <pevz:kontakt id="8848386">
        <pevz:einrichtung id="8838326">
            <pevz:name>Institut für interdisziplinäre Konflikt- und Gewaltforschung / Wissenschaftlicher Beirat</pevz:name>
            <pevz:name_en>Institute for Interdisciplinary Research on Conflict and Violence / Wissenschaftlicher Beirat</pevz:name_en>
        </pevz:einrichtung>
        <pevz:funktion>Wissenschaftlicher Beirat</pevz:funktion>
        <pevz:email></pevz:email>
        <pevz:email_verschleiert></pevz:email_verschleiert>
        <pevz:url>http://www.asw-trier.de/index.php?id=44</pevz:url>
        <pevz:telefon></pevz:telefon>
        <pevz:fax></pevz:fax>
        <pevz:telefon_sekretariat></pevz:telefon_sekretariat>
        <pevz:raum></pevz:raum>
        <pevz:sprechzeiten></pevz:sprechzeiten>
        <pevz:profs>nein</pevz:profs>
    </pevz:kontakt>
</pevz:kontakte>
