<?xml version="1.0" encoding="UTF-8"?>
<pevz:kontakte personid="171789" xmlns:pevz="http://ekvv.uni-bielefeld.de/pers_publ/">
    <pevz:kontakt id="11572316">
        <pevz:einrichtung id="10023">
            <pevz:name>Fakultät für Geschichtswissenschaft, Philosophie und Theologie / Abteilung Geschichte</pevz:name>
            <pevz:name_en>Faculty of History, Philosophy and Theology / Department of History</pevz:name_en>
        </pevz:einrichtung>
        <pevz:funktion>Geschichte des Hoch- und Spätmittelalters</pevz:funktion>
        <pevz:email>franz.arlinghaus@uni-bielefeld.de</pevz:email>
        <pevz:email_verschleiert>&amp;#102;ran&amp;#122;.ar&amp;#108;ing&amp;#104;aus&amp;#64;uni&amp;#45;bie&amp;#108;efe&amp;#108;d.d&amp;#101;</pevz:email_verschleiert>
        <pevz:url>http://www.franzarlinghaus.de</pevz:url>
        <pevz:telefon>3260</pevz:telefon>
        <pevz:fax>2966</pevz:fax>
        <pevz:telefon_sekretariat>3264</pevz:telefon_sekretariat>
        <pevz:raum>Gebäude X A3-222</pevz:raum>
        <pevz:sprechzeiten>Im Semester Fr 15 - 16 Uhr</pevz:sprechzeiten>
        <pevz:profs>ja</pevz:profs>
    </pevz:kontakt>
    <pevz:kontakt id="12813277">
        <pevz:einrichtung id="3652153">
            <pevz:name>Fakultät für Geschichtswissenschaft, Philosophie und Theologie / Abteilung Geschichte / Schule für Historische Forschung</pevz:name>
            <pevz:name_en>Faculty of History, Philosophy and Theology / Department of History / Schule für Historische Forschung</pevz:name_en>
        </pevz:einrichtung>
        <pevz:funktion></pevz:funktion>
        <pevz:email></pevz:email>
        <pevz:email_verschleiert></pevz:email_verschleiert>
        <pevz:url></pevz:url>
        <pevz:telefon></pevz:telefon>
        <pevz:fax></pevz:fax>
        <pevz:telefon_sekretariat></pevz:telefon_sekretariat>
        <pevz:raum></pevz:raum>
        <pevz:sprechzeiten></pevz:sprechzeiten>
        <pevz:profs>nein</pevz:profs>
    </pevz:kontakt>
    <pevz:kontakt id="36269156">
        <pevz:einrichtung id="3791087">
            <pevz:name>Fakultät für Geschichtswissenschaft, Philosophie und Theologie / Abteilung Geschichte / Geschichte des Mittelalters und der Frühen Neuzeit</pevz:name>
            <pevz:name_en>Faculty of History, Philosophy and Theology / Department of History / Geschichte des Mittelalters und der Frühen Neuzeit</pevz:name_en>
        </pevz:einrichtung>
        <pevz:funktion></pevz:funktion>
        <pevz:email></pevz:email>
        <pevz:email_verschleiert></pevz:email_verschleiert>
        <pevz:url></pevz:url>
        <pevz:telefon></pevz:telefon>
        <pevz:fax></pevz:fax>
        <pevz:telefon_sekretariat></pevz:telefon_sekretariat>
        <pevz:raum></pevz:raum>
        <pevz:sprechzeiten></pevz:sprechzeiten>
        <pevz:profs>nein</pevz:profs>
    </pevz:kontakt>
    <pevz:kontakt id="19598254">
        <pevz:einrichtung id="34961736">
            <pevz:name>Fakultät für Geschichtswissenschaft, Philosophie und Theologie / Abteilung Geschichte / Geschichte des Hoch- und Spätmittelalters</pevz:name>
            <pevz:name_en>Faculty of History, Philosophy and Theology / Department of History / Geschichte des Hoch- und Spätmittelalters</pevz:name_en>
        </pevz:einrichtung>
        <pevz:funktion></pevz:funktion>
        <pevz:email></pevz:email>
        <pevz:email_verschleiert></pevz:email_verschleiert>
        <pevz:url></pevz:url>
        <pevz:telefon></pevz:telefon>
        <pevz:fax></pevz:fax>
        <pevz:telefon_sekretariat></pevz:telefon_sekretariat>
        <pevz:raum></pevz:raum>
        <pevz:sprechzeiten></pevz:sprechzeiten>
        <pevz:profs>nein</pevz:profs>
    </pevz:kontakt>
    <pevz:kontakt id="32752245">
        <pevz:einrichtung id="32589619">
            <pevz:name>BiSEd-Mitglieder</pevz:name>
            <pevz:name_en>BiSEd-Mitglieder</pevz:name_en>
        </pevz:einrichtung>
        <pevz:funktion></pevz:funktion>
        <pevz:email></pevz:email>
        <pevz:email_verschleiert></pevz:email_verschleiert>
        <pevz:url></pevz:url>
        <pevz:telefon></pevz:telefon>
        <pevz:fax></pevz:fax>
        <pevz:telefon_sekretariat></pevz:telefon_sekretariat>
        <pevz:raum></pevz:raum>
        <pevz:sprechzeiten></pevz:sprechzeiten>
        <pevz:profs>nein</pevz:profs>
    </pevz:kontakt>
</pevz:kontakte>
