<?xml version="1.0" encoding="UTF-8"?>
<pevz:kontakte personid="33699786" xmlns:pevz="http://ekvv.uni-bielefeld.de/pers_publ/">
    <pevz:kontakt id="33699787">
        <pevz:einrichtung id="201230">
            <pevz:name>Technische Fakultät / AG Biomathematik und Theoretische Bioinformatik</pevz:name>
            <pevz:name_en>Faculty of Technology / AG Biomathematik und Theoretische Bioinformatik</pevz:name_en>
        </pevz:einrichtung>
        <pevz:funktion></pevz:funktion>
        <pevz:email>messer@techfak.uni-bielefeld.de</pevz:email>
        <pevz:email_verschleiert>&amp;#109;ess&amp;#101;r@t&amp;#101;chf&amp;#97;k.u&amp;#110;i-b&amp;#105;ele&amp;#102;eld&amp;#46;de</pevz:email_verschleiert>
        <pevz:url>http://www.techfak.uni-bielefeld.de/ags/bm/people/messer.htm</pevz:url>
        <pevz:telefon>3855</pevz:telefon>
        <pevz:fax>6411</pevz:fax>
        <pevz:telefon_sekretariat></pevz:telefon_sekretariat>
        <pevz:raum>UHG U4-141</pevz:raum>
        <pevz:sprechzeiten></pevz:sprechzeiten>
        <pevz:profs>nein</pevz:profs>
    </pevz:kontakt>
    <pevz:kontakt id="61053671">
        <pevz:einrichtung id="201230">
            <pevz:name>Technische Fakultät / AG Biomathematik und Theoretische Bioinformatik</pevz:name>
            <pevz:name_en>Faculty of Technology / AG Biomathematik und Theoretische Bioinformatik</pevz:name_en>
        </pevz:einrichtung>
        <pevz:funktion>Sekretariat</pevz:funktion>
        <pevz:email></pevz:email>
        <pevz:email_verschleiert></pevz:email_verschleiert>
        <pevz:url></pevz:url>
        <pevz:telefon></pevz:telefon>
        <pevz:fax></pevz:fax>
        <pevz:telefon_sekretariat></pevz:telefon_sekretariat>
        <pevz:raum></pevz:raum>
        <pevz:sprechzeiten></pevz:sprechzeiten>
        <pevz:profs>nein</pevz:profs>
    </pevz:kontakt>
</pevz:kontakte>
