<?xml version="1.0" encoding="UTF-8"?>
<pevz:kontakte personid="49877273" xmlns:pevz="http://ekvv.uni-bielefeld.de/pers_publ/">
    <pevz:kontakt id="49877274">
        <pevz:einrichtung id="26688499">
            <pevz:name>SFB 882 Von Heterogenitäten zu Ungleichheiten / Projektbereich B / Teilprojekt B3</pevz:name>
            <pevz:name_en>CRC 882 From Heterogeneities to Inequalities / Project Area B / Project B3</pevz:name_en>
        </pevz:einrichtung>
        <pevz:funktion>Wiss. Mit. Teilprojekt B3</pevz:funktion>
        <pevz:email>bjoern.andernach@uni-bielefeld.de</pevz:email>
        <pevz:email_verschleiert>&amp;#98;j&amp;#111;e&amp;#114;n&amp;#46;a&amp;#110;d&amp;#101;r&amp;#110;a&amp;#99;h&amp;#64;u&amp;#110;i&amp;#45;b&amp;#105;e&amp;#108;e&amp;#102;e&amp;#108;d&amp;#46;d&amp;#101;</pevz:email_verschleiert>
        <pevz:url></pevz:url>
        <pevz:telefon>12180</pevz:telefon>
        <pevz:fax></pevz:fax>
        <pevz:telefon_sekretariat></pevz:telefon_sekretariat>
        <pevz:raum>Gebäude X E1-269</pevz:raum>
        <pevz:sprechzeiten></pevz:sprechzeiten>
        <pevz:profs>nein</pevz:profs>
    </pevz:kontakt>
    <pevz:kontakt id="52618982">
        <pevz:einrichtung id="17799615">
            <pevz:name>Fakultät für Soziologie / Personen / Wissenschaftliche MitarbeiterInnen in Forschungsprojekten</pevz:name>
            <pevz:name_en>Faculty of Sociology / Personen / Wissenschaftliche MitarbeiterInnen in Forschungsprojekten</pevz:name_en>
        </pevz:einrichtung>
        <pevz:funktion>Wiss. Mit. (SFB 882)</pevz:funktion>
        <pevz:email></pevz:email>
        <pevz:email_verschleiert></pevz:email_verschleiert>
        <pevz:url></pevz:url>
        <pevz:telefon></pevz:telefon>
        <pevz:fax></pevz:fax>
        <pevz:telefon_sekretariat></pevz:telefon_sekretariat>
        <pevz:raum></pevz:raum>
        <pevz:sprechzeiten></pevz:sprechzeiten>
        <pevz:profs>nein</pevz:profs>
    </pevz:kontakt>
    <pevz:kontakt id="52619928">
        <pevz:einrichtung id="5656055">
            <pevz:name>Fakultät für Soziologie / Arbeitsbereiche / Arbeitsbereich 5 - Sozialstruktur und soziale Ungleichheit</pevz:name>
            <pevz:name_en>Faculty of Sociology / Arbeitsbereiche / Arbeitsbereich 5 - Sozialstruktur und soziale Ungleichheit</pevz:name_en>
        </pevz:einrichtung>
        <pevz:funktion>Projektmitarbeiter (SFB 882)</pevz:funktion>
        <pevz:email></pevz:email>
        <pevz:email_verschleiert></pevz:email_verschleiert>
        <pevz:url></pevz:url>
        <pevz:telefon></pevz:telefon>
        <pevz:fax></pevz:fax>
        <pevz:telefon_sekretariat></pevz:telefon_sekretariat>
        <pevz:raum></pevz:raum>
        <pevz:sprechzeiten></pevz:sprechzeiten>
        <pevz:profs>nein</pevz:profs>
    </pevz:kontakt>
</pevz:kontakte>
