<?xml version="1.0" encoding="UTF-8"?>
<pevz:kontakte personid="35001160" xmlns:pevz="http://ekvv.uni-bielefeld.de/pers_publ/">
    <pevz:kontakt id="45780114">
        <pevz:einrichtung id="36514258">
            <pevz:name>Fakult채t f체r Linguistik und Literaturwissenschaft / Studienf채cher / Kunst- und Musikp채dagogik / Lehrbeauftragte</pevz:name>
            <pevz:name_en>Faculty of Linguistics and Literary Studies / Fields of Study  /  Departments / Art and Music education / contract teacher</pevz:name_en>
        </pevz:einrichtung>
        <pevz:funktion></pevz:funktion>
        <pevz:email>peter.auslaender@fh-bielefeld.de</pevz:email>
        <pevz:email_verschleiert>&amp;#112;e&amp;#116;e&amp;#114;.&amp;#97;u&amp;#115;l&amp;#97;e&amp;#110;d&amp;#101;r&amp;#64;f&amp;#104;-&amp;#98;i&amp;#101;l&amp;#101;f&amp;#101;l&amp;#100;.&amp;#100;e</pevz:email_verschleiert>
        <pevz:url></pevz:url>
        <pevz:telefon></pevz:telefon>
        <pevz:fax></pevz:fax>
        <pevz:telefon_sekretariat>6072</pevz:telefon_sekretariat>
        <pevz:raum></pevz:raum>
        <pevz:sprechzeiten></pevz:sprechzeiten>
        <pevz:profs>nein</pevz:profs>
    </pevz:kontakt>
</pevz:kontakte>
