<?xml version='1.0'?>

<searchRetrieveResponse xmlns="http://www.loc.gov/zing/srw/">
<version>1.1</version>
<numberOfRecords>1</numberOfRecords>
<records>
<record><recordSchema>info:srw/schema/1/mods-v3.3</recordSchema><recordPacking>xml</recordPacking><recordData>
<mods version="3.3"
      xmlns:xlink="http://www.w3.org/1999/xlink"
      xmlns:xsi="http://www.w3.org/2001/XMLSchema-instance"
      xmlns="http://www.loc.gov/mods/v3"
      xsi:schemaLocation="http://www.loc.gov/mods/v3 http://www.loc.gov/standards/mods/v3/mods-3-3.xsd">
<genre>book</genre>

<titleInfo><title>Zum aktuellen Diskurs um Ergebnisse und Wirkungen im Feld der Sozialpädagogik und Sozialarbeit - Literaturvergleich nationaler und internationaler Diskussion. Expertise im Auftrag der Arbeitsgemeinschaft für Kinder- und Jugendhilfe – AGJ</title></titleInfo>





<name type="personal">
  <namePart type="given">Hans-Uwe</namePart>
  <namePart type="family">Otto</namePart>
  <role><roleTerm type="text">author</roleTerm> </role><identifier type="unibi">21770</identifier></name>
<name type="personal">
  <namePart type="given">Stefanie</namePart>
  <namePart type="family">Albus</namePart>
  <role><roleTerm type="text">author</roleTerm> </role><identifier type="unibi">179180</identifier></name>
<name type="personal">
  <namePart type="given">Andreas</namePart>
  <namePart type="family">Polutta</namePart>
  <role><roleTerm type="text">author</roleTerm> </role><identifier type="unibi">176117</identifier></name>
<name type="personal">
  <namePart type="given">Mark</namePart>
  <namePart type="family">Schrödter</namePart>
  <role><roleTerm type="text">author</roleTerm> </role></name>
<name type="personal">
  <namePart type="given">Holger</namePart>
  <namePart type="family">Ziegler</namePart>
  <role><roleTerm type="text">author</roleTerm> </role><identifier type="unibi">108507</identifier></name>







<name type="corporate">
  <namePart>Fakultät für Erziehungswissenschaft</namePart>
  <identifier type="unibi">10021</identifier>
  <role>
    <roleTerm type="text">department</roleTerm>
  </role>
</name>

<name type="corporate">
  <namePart>AG 8 - Soziale Arbeit</namePart>
  <identifier type="unibi">7978278</identifier>
  <role>
    <roleTerm type="text">department</roleTerm>
  </role>
</name>









<originInfo><publisher>AGJ</publisher><dateIssued encoding="w3cdtf">2007</dateIssued>
</originInfo>
<language><languageTerm authority="iso639-2b" type="code">ger</languageTerm>
</language>



<relatedItem type="host">
<part>
</part>
</relatedItem>

<note type="nonBielefeld">yes</note>
<extension>
<bibliographicCitation>
<ieee>H.-U. Otto, et al., &lt;em&gt;Zum aktuellen Diskurs um Ergebnisse und Wirkungen im Feld der Sozialpädagogik und Sozialarbeit - Literaturvergleich nationaler und internationaler Diskussion. Expertise im Auftrag der Arbeitsgemeinschaft für Kinder- und Jugendhilfe – AGJ&lt;/em&gt;,  Berlin: AGJ, 2007.</ieee>
<lncs>Otto, H.-U., Albus, S., Polutta, A., Schrödter, M., Ziegler, H.: Zum aktuellen Diskurs um Ergebnisse und Wirkungen im Feld der Sozialpädagogik und Sozialarbeit - Literaturvergleich nationaler und internationaler Diskussion. Expertise im Auftrag der Arbeitsgemeinschaft für Kinder- und Jugendhilfe – AGJ. AGJ, Berlin (2007).</lncs>
<mla>Otto, Hans-Uwe, Albus, Stefanie, Polutta, Andreas, Schrödter, Mark, and Ziegler, Holger. &lt;em&gt;Zum aktuellen Diskurs um Ergebnisse und Wirkungen im Feld der Sozialpädagogik und Sozialarbeit - Literaturvergleich nationaler und internationaler Diskussion. Expertise im Auftrag der Arbeitsgemeinschaft für Kinder- und Jugendhilfe – AGJ&lt;/em&gt;. Berlin: AGJ, 2007.</mla>
<apa_indent>&lt;div style=&quot;text-indent:-25px; padding-left:25px;padding-bottom:0px;&quot;&gt;Otto, H. - U., Albus, S., Polutta, A., Schrödter, M., &amp;amp; Ziegler, H. (2007).  &lt;em&gt;Zum aktuellen Diskurs um Ergebnisse und Wirkungen im Feld der Sozialpädagogik und Sozialarbeit - Literaturvergleich nationaler und internationaler Diskussion. Expertise im Auftrag der Arbeitsgemeinschaft für Kinder- und Jugendhilfe – AGJ&lt;/em&gt;. Berlin: AGJ.&lt;/div&gt;</apa_indent>
<angewandte-chemie>H. - U.  Otto, S.  Albus, A.  Polutta, M.  Schrödter, and H.  Ziegler, &lt;em&gt;Zum aktuellen Diskurs um Ergebnisse und Wirkungen im Feld der Sozialpädagogik und Sozialarbeit - Literaturvergleich nationaler und internationaler Diskussion. Expertise im Auftrag der Arbeitsgemeinschaft für Kinder- und Jugendhilfe – AGJ&lt;/em&gt;, Agj, Berlin, &lt;strong&gt;2007&lt;/strong&gt;.</angewandte-chemie>
<apa>Otto, H. - U., Albus, S., Polutta, A., Schrödter, M., &amp;amp; Ziegler, H. (2007).  &lt;em&gt;Zum aktuellen Diskurs um Ergebnisse und Wirkungen im Feld der Sozialpädagogik und Sozialarbeit - Literaturvergleich nationaler und internationaler Diskussion. Expertise im Auftrag der Arbeitsgemeinschaft für Kinder- und Jugendhilfe – AGJ&lt;/em&gt;. Berlin: AGJ.</apa>
<frontiers>Otto, H. - U., Albus, S., Polutta, A., Schrödter, M., and Ziegler, H. (2007). Zum aktuellen Diskurs um Ergebnisse und Wirkungen im Feld der Sozialpädagogik und Sozialarbeit - Literaturvergleich nationaler und internationaler Diskussion. Expertise im Auftrag der Arbeitsgemeinschaft für Kinder- und Jugendhilfe – AGJ. Berlin: AGJ.</frontiers>
<chicago>&lt;div style=&quot;text-indent:-25px; padding-left:25px;padding-bottom:0px;&quot;&gt;Otto, Hans-Uwe, Albus, Stefanie, Polutta, Andreas, Schrödter, Mark, and Ziegler, Holger. 2007. &lt;em&gt;Zum aktuellen Diskurs um Ergebnisse und Wirkungen im Feld der Sozialpädagogik und Sozialarbeit - Literaturvergleich nationaler und internationaler Diskussion. Expertise im Auftrag der Arbeitsgemeinschaft für Kinder- und Jugendhilfe – AGJ&lt;/em&gt;. Berlin: AGJ.&lt;/div&gt;</chicago>
<harvard1>Otto, H.-U., et al., 2007. &lt;em&gt;Zum aktuellen Diskurs um Ergebnisse und Wirkungen im Feld der Sozialpädagogik und Sozialarbeit - Literaturvergleich nationaler und internationaler Diskussion. Expertise im Auftrag der Arbeitsgemeinschaft für Kinder- und Jugendhilfe – AGJ&lt;/em&gt;, Berlin: AGJ.</harvard1>
<ama>Otto H-U, Albus S, Polutta A, Schrödter M, Ziegler H. &lt;em&gt;Zum aktuellen Diskurs um Ergebnisse und Wirkungen im Feld der Sozialpädagogik und Sozialarbeit - Literaturvergleich nationaler und internationaler Diskussion. Expertise im Auftrag der Arbeitsgemeinschaft für Kinder- und Jugendhilfe – AGJ&lt;/em&gt;. Berlin: AGJ; 2007.</ama>
<dgps>&lt;div style=&quot;text-indent:-25px; padding-left:25px;padding-bottom:0px;&quot;&gt;Otto, H.-U., Albus, S., Polutta, A., Schrödter, M. &amp;amp; Ziegler, H. (2007). &lt;em&gt;Zum aktuellen Diskurs um Ergebnisse und Wirkungen im Feld der Sozialpädagogik und Sozialarbeit - Literaturvergleich nationaler und internationaler Diskussion. Expertise im Auftrag der Arbeitsgemeinschaft für Kinder- und Jugendhilfe – AGJ&lt;/em&gt;. Berlin: AGJ.&lt;/div&gt;</dgps>
<bio1>Otto H-U, Albus S, Polutta A, Schrödter M, Ziegler H (2007) &lt;br /&gt;&lt;em&gt;Zum aktuellen Diskurs um Ergebnisse und Wirkungen im Feld der Sozialpädagogik und Sozialarbeit - Literaturvergleich nationaler und internationaler Diskussion. Expertise im Auftrag der Arbeitsgemeinschaft für Kinder- und Jugendhilfe – AGJ&lt;/em&gt;.&lt;br /&gt;Berlin: AGJ.</bio1>
<aps>H. - U.  Otto, et al., Zum aktuellen Diskurs um Ergebnisse und Wirkungen im Feld der Sozialpädagogik und Sozialarbeit - Literaturvergleich nationaler und internationaler Diskussion. Expertise im Auftrag der Arbeitsgemeinschaft für Kinder- und Jugendhilfe – AGJ, (AGJ, Berlin, 2007).</aps>
<wels>Otto, H. - U.; Albus, S.; Polutta, A.; Schrödter, M.; Ziegler, H. (2007): Zum aktuellen Diskurs um Ergebnisse und Wirkungen im Feld der Sozialpädagogik und Sozialarbeit - Literaturvergleich nationaler und internationaler Diskussion. Expertise im Auftrag der Arbeitsgemeinschaft für Kinder- und Jugendhilfe – AGJ. Berlin: AGJ.</wels>
<default>Otto H-U, Albus S, Polutta A, Schrödter M, Ziegler H (2007) &lt;br /&gt;Berlin: AGJ.</default>
</bibliographicCitation>
</extension>
<recordInfo><recordIdentifier>1914951</recordIdentifier><recordCreationDate encoding="w3cdtf">2010-11-15T11:27:00Z</recordCreationDate><recordChangeDate encoding="w3cdtf">2011-03-21T08:45:41Z</recordChangeDate>
</recordInfo>
</mods>
</recordData><recordPosition>1</recordPosition></record>
</records>

<extraResponseData></extraResponseData> 
<echoedSearchRetrieveRequest><version>1.1</version><query>id=1914951</query><xQuery><searchClause xmlns="http://www.loc.gov/zing/cql/xcql/"><index>id</index><relation><value>=</value></relation><term>1914951</term></searchClause></xQuery></echoedSearchRetrieveRequest>
</searchRetrieveResponse>
