<?xml version='1.0'?>

<searchRetrieveResponse xmlns="http://www.loc.gov/zing/srw/">
<version>1.1</version>
<numberOfRecords>1</numberOfRecords>
<records>
<record><recordSchema>info:srw/schema/1/mods-v3.3</recordSchema><recordPacking>xml</recordPacking><recordData>
<mods version="3.3"
      xmlns:xlink="http://www.w3.org/1999/xlink"
      xmlns:xsi="http://www.w3.org/2001/XMLSchema-instance"
      xmlns="http://www.loc.gov/mods/v3"
      xsi:schemaLocation="http://www.loc.gov/mods/v3 http://www.loc.gov/standards/mods/v3/mods-3-3.xsd">
<genre>article</genre>

<titleInfo><title>Attentional shifts to rare singletons</title></titleInfo>


<note type="publicationStatus">published</note>


<note type="qualityControlled">yes</note>

<name type="personal">
  <namePart type="given">Gernot</namePart>
  <namePart type="family">Horstmann</namePart>
  <role><roleTerm type="text">author</roleTerm> </role><identifier type="unibi">34315</identifier></name>
<name type="personal">
  <namePart type="given">Ulrich</namePart>
  <namePart type="family">Ansorge</namePart>
  <role><roleTerm type="text">author</roleTerm> </role></name>







<name type="corporate">
  <namePart></namePart>
  <identifier type="unibi">10026</identifier>
  <role>
    <roleTerm type="text">department</roleTerm>
  </role>
</name>








<abstract lang="eng">Five experiments examined whether extremely rare featural singletons (e. g., presented in 4% of all trials) capture attention, and whether this effect could be explained by top-down contingent capture or stimulus-driven singleton capture. To this end, performance (accuracy in Experiments 1-4, reaction time in Experiment 5) in a demanding letter search task was measured in singleton trials that were presented within rare-singleton blocks consisting mainly of no-singleton trials, and in singleton trials that occurred in all-singleton blocks. In separate blocks, either target singletons (i.e., a singleton at target position), or distractor singletons (i.e., a singleton at a distractor position) were presented in each trial. Results are consistent with the contingent-capture view. When the letters were presented briefly and accuracy was the dependent variable, a large performance benefit was obtained, revealing that attention was shifted very fast to the singleton. An examination of search efficiency with a variation of set size and reaction time as the dependent variable revealed a strong gain in search efficiency with a rare target singleton. The large benefit was not accompanied by proportionally large costs for distractor singletons relative to the no-distractor trials. Moreover, a comparison of singleton trials from the all-singleton and from the rare-singleton blocks revealed nonspatial costs for the rare singletons that were of about the same size for target and distractor singletons. In summary, results show that an attentional control setting can remain &quot;dormant&apos;&apos; for many trials where it is not applicable, but is then applied nearly as efficiently as when the control setting has been used just recently.</abstract>

<originInfo><publisher>PSYCHOLOGY PRESS</publisher><dateIssued encoding="w3cdtf">2006</dateIssued>
</originInfo>
<language><languageTerm authority="iso639-2b" type="code">eng</languageTerm>
</language>



<relatedItem type="host"><titleInfo><title>VISUAL COGNITION</title></titleInfo>
  <identifier type="issn">1350-6285</identifier>
  <identifier type="eIssn">1464-0716</identifier>
  <identifier type="ISI">000238247200002</identifier><identifier type="doi">10.1080/13506280500236492</identifier>
<part><detail type="volume"><number>14</number></detail><detail type="issue"><number>3</number></detail><extent unit="pages">295-325</extent>
</part>
</relatedItem>


<extension>
<bibliographicCitation>
<ama>Horstmann G, Ansorge U. Attentional shifts to rare singletons. &lt;em&gt;VISUAL COGNITION&lt;/em&gt;. 2006;14(3):295-325.</ama>
<dgps>&lt;div style=&quot;text-indent:-25px; padding-left:25px;padding-bottom:0px;&quot;&gt;Horstmann, G. &amp;amp; Ansorge, U. (2006). Attentional shifts to rare singletons. &lt;em&gt;VISUAL COGNITION&lt;/em&gt;, &lt;em&gt;14&lt;/em&gt;(3), 295-325. PSYCHOLOGY PRESS. doi:10.1080/13506280500236492.&lt;/div&gt;</dgps>
<harvard1>Horstmann, G., &amp;amp; Ansorge, U., 2006. Attentional shifts to rare singletons. &lt;em&gt;VISUAL COGNITION&lt;/em&gt;, 14(3), p 295-325.</harvard1>
<aps> G.  Horstmann and U.  Ansorge, Attentional shifts to rare singletons, VISUAL COGNITION &lt;strong&gt;14&lt;/strong&gt;, 295-325 (2006).</aps>
<bio1>Horstmann G, Ansorge U (2006) &lt;br /&gt;Attentional shifts to rare singletons.&lt;br /&gt;VISUAL COGNITION 14(3): 295-325.</bio1>
<wels>Horstmann, G.; Ansorge, U. (2006): Attentional shifts to rare singletons &lt;em&gt;VISUAL COGNITION&lt;/em&gt;,14:(3): 295-325.</wels>
<default>Horstmann G, Ansorge U (2006) &lt;br /&gt;VISUAL COGNITION 14(3): 295-325.</default>
<ieee> G. Horstmann and U. Ansorge, “Attentional shifts to rare singletons”, &lt;em&gt;VISUAL COGNITION&lt;/em&gt;,  vol. 14, 2006,  pp. 295-325.</ieee>
<lncs> Horstmann, G., Ansorge, U.: Attentional shifts to rare singletons. VISUAL COGNITION. 14, 295-325 (2006).</lncs>
<mla>Horstmann, Gernot, and Ansorge, Ulrich. “Attentional shifts to rare singletons”. &lt;em&gt;VISUAL COGNITION&lt;/em&gt; 14.3 (2006): 295-325.</mla>
<apa_indent>&lt;div style=&quot;text-indent:-25px; padding-left:25px;padding-bottom:0px;&quot;&gt;Horstmann, G., &amp;amp; Ansorge, U. (2006). Attentional shifts to rare singletons. &lt;em&gt;VISUAL COGNITION&lt;/em&gt;, &lt;em&gt;14&lt;/em&gt;(3), 295-325.&lt;/div&gt;</apa_indent>
<angewandte-chemie>G.  Horstmann, and U.  Ansorge, “Attentional shifts to rare singletons”, &lt;em&gt;VISUAL COGNITION&lt;/em&gt;, &lt;strong&gt;2006&lt;/strong&gt;, &lt;em&gt;14&lt;/em&gt;, 295-325.</angewandte-chemie>
<apa>Horstmann, G., &amp;amp; Ansorge, U. (2006). Attentional shifts to rare singletons. &lt;em&gt;VISUAL COGNITION&lt;/em&gt;, &lt;em&gt;14&lt;/em&gt;(3), 295-325.</apa>
<frontiers>Horstmann, G., and Ansorge, U. (2006). Attentional shifts to rare singletons. &lt;em&gt;VISUAL COGNITION&lt;/em&gt; 14, 295-325.</frontiers>
<chicago>&lt;div style=&quot;text-indent:-25px; padding-left:25px;padding-bottom:0px;&quot;&gt;Horstmann, Gernot, and Ansorge, Ulrich. 2006. “Attentional shifts to rare singletons”. &lt;em&gt;VISUAL COGNITION&lt;/em&gt; 14 (3): 295-325.&lt;/div&gt;</chicago>
</bibliographicCitation>
</extension>
<recordInfo><recordIdentifier>1598857</recordIdentifier><recordCreationDate encoding="w3cdtf">2010-04-28T12:19:38Z</recordCreationDate><recordChangeDate encoding="w3cdtf">2016-10-13T13:04:03Z</recordChangeDate>
</recordInfo>
</mods>
</recordData><recordPosition>1</recordPosition></record>
</records>

<extraResponseData></extraResponseData> 
<echoedSearchRetrieveRequest><version>1.1</version><query>id=1598857</query><xQuery><searchClause xmlns="http://www.loc.gov/zing/cql/xcql/"><index>id</index><relation><value>=</value></relation><term>1598857</term></searchClause></xQuery></echoedSearchRetrieveRequest>
</searchRetrieveResponse>
