<?xml version='1.0'?>

<searchRetrieveResponse xmlns="http://www.loc.gov/zing/srw/">
<version>1.1</version>
<numberOfRecords>1</numberOfRecords>
<records>
<record><recordSchema>info:srw/schema/1/mods-v3.3</recordSchema><recordPacking>xml</recordPacking><recordData>
<mods version="3.3"
      xmlns:xlink="http://www.w3.org/1999/xlink"
      xmlns:xsi="http://www.w3.org/2001/XMLSchema-instance"
      xmlns="http://www.loc.gov/mods/v3"
      xsi:schemaLocation="http://www.loc.gov/mods/v3 http://www.loc.gov/standards/mods/v3/mods-3-3.xsd">
<genre>article</genre>

<titleInfo><title>Color screening and deconfinement for bound states of heavy quarks</title></titleInfo>


<note type="publicationStatus">published</note>



<name type="personal">
  <namePart type="given">Frithjof</namePart>
  <namePart type="family">Karsch</namePart>
  <role><roleTerm type="text">author</roleTerm> </role><identifier type="unibi">40326</identifier></name>
<name type="personal">
  <namePart type="given">M. T.</namePart>
  <namePart type="family">Mehr</namePart>
  <role><roleTerm type="text">author</roleTerm> </role></name>
<name type="personal">
  <namePart type="given">Helmut</namePart>
  <namePart type="family">Satz</namePart>
  <role><roleTerm type="text">author</roleTerm> </role><identifier type="unibi">40339</identifier></name>







<name type="corporate">
  <namePart>AG Phänomenologie von Schwerionenkollisionen</namePart>
  <identifier type="unibi">23470601</identifier>
  <role>
    <roleTerm type="text">department</roleTerm>
  </role>
</name>

<name type="corporate">
  <namePart>AG Computersimulationen und Gitterfeldtheorie</namePart>
  <identifier type="unibi">23470456</identifier>
  <role>
    <roleTerm type="text">department</roleTerm>
  </role>
</name>









<relatedItem type="constituent">
  <location>
    <url displayLabel="ka_46.pdf">https://pub.uni-bielefeld.de/download/1784493/2314457</url>
  </location>
  <physicalDescription><internetMediaType>application/pdf</internetMediaType></physicalDescription><accessCondition type="restrictionOnAccess">no</accessCondition>
</relatedItem>
<originInfo><dateIssued encoding="w3cdtf">1988</dateIssued>
</originInfo>
<language><languageTerm authority="iso639-2b" type="code">eng</languageTerm>
</language>



<relatedItem type="host"><titleInfo><title>Zeitschrift für Physik, C: Particles and Fields</title></titleInfo>
  <identifier type="issn">0170-9739</identifier>
  <identifier type="eIssn">1434-6052</identifier>
  <identifier type="INSPIRE">248029</identifier>
  <identifier type="ISI">A1988M670300014</identifier><identifier type="urn">urn:nbn:de:0070-pub-17844939</identifier><identifier type="doi">10.1007/BF01549722</identifier>
<part><detail type="volume"><number>37</number></detail><detail type="issue"><number>4</number></detail><extent unit="pages">617-622</extent>
</part>
</relatedItem>


<extension>
<bibliographicCitation>
<frontiers>Karsch, F., Mehr, M. T., and Satz, H. (1988). Color screening and deconfinement for bound states of heavy quarks. &lt;em&gt;Zeitschrift für Physik, C: Particles and Fields&lt;/em&gt; 37, 617-622.</frontiers>
<angewandte-chemie>F.  Karsch, M. T.  Mehr, and H.  Satz, “Color screening and deconfinement for bound states of heavy quarks”, &lt;em&gt;Zeitschrift für Physik, C: Particles and Fields&lt;/em&gt;, &lt;strong&gt;1988&lt;/strong&gt;, &lt;em&gt;37&lt;/em&gt;, 617-622.</angewandte-chemie>
<apa>Karsch, F., Mehr, M. T., &amp;amp; Satz, H. (1988). Color screening and deconfinement for bound states of heavy quarks. &lt;em&gt;Zeitschrift für Physik, C: Particles and Fields&lt;/em&gt;, &lt;em&gt;37&lt;/em&gt;(4), 617-622.</apa>
<chicago>&lt;div style=&quot;text-indent:-25px; padding-left:25px;padding-bottom:0px;&quot;&gt;Karsch, Frithjof, Mehr, M. T., and Satz, Helmut. 1988. “Color screening and deconfinement for bound states of heavy quarks”. &lt;em&gt;Zeitschrift für Physik, C: Particles and Fields&lt;/em&gt; 37 (4): 617-622.&lt;/div&gt;</chicago>
<lncs>Karsch, F., Mehr, M.T., Satz, H.: Color screening and deconfinement for bound states of heavy quarks. Zeitschrift für Physik, C: Particles and Fields. 37, 617-622 (1988).</lncs>
<mla>Karsch, Frithjof, Mehr, M. T., and Satz, Helmut. “Color screening and deconfinement for bound states of heavy quarks”. &lt;em&gt;Zeitschrift für Physik, C: Particles and Fields&lt;/em&gt; 37.4 (1988): 617-622.</mla>
<ieee>F. Karsch, M.T. Mehr, and H. Satz, “Color screening and deconfinement for bound states of heavy quarks”, &lt;em&gt;Zeitschrift für Physik, C: Particles and Fields&lt;/em&gt;,  vol. 37, 1988,  pp. 617-622.</ieee>
<apa_indent>&lt;div style=&quot;text-indent:-25px; padding-left:25px;padding-bottom:0px;&quot;&gt;Karsch, F., Mehr, M. T., &amp;amp; Satz, H. (1988). Color screening and deconfinement for bound states of heavy quarks. &lt;em&gt;Zeitschrift für Physik, C: Particles and Fields&lt;/em&gt;, &lt;em&gt;37&lt;/em&gt;(4), 617-622.&lt;/div&gt;</apa_indent>
<default>Karsch F, Mehr MT, Satz H (1988) &lt;br /&gt;Zeitschrift für Physik, C: Particles and Fields 37(4): 617-622.</default>
<wels>Karsch, F.; Mehr, M. T.; Satz, H. (1988): Color screening and deconfinement for bound states of heavy quarks &lt;em&gt;Zeitschrift für Physik, C: Particles and Fields&lt;/em&gt;,37:(4): 617-622.</wels>
<bio1>Karsch F, Mehr MT, Satz H (1988) &lt;br /&gt;Color screening and deconfinement for bound states of heavy quarks.&lt;br /&gt;Zeitschrift für Physik, C: Particles and Fields 37(4): 617-622.</bio1>
<aps>F.  Karsch, M. T.  Mehr, and H.  Satz, Color screening and deconfinement for bound states of heavy quarks, Zeitschrift für Physik, C: Particles and Fields &lt;strong&gt;37&lt;/strong&gt;, 617-622 (1988).</aps>
<harvard1>Karsch, F., Mehr, M.T., &amp;amp; Satz, H., 1988. Color screening and deconfinement for bound states of heavy quarks. &lt;em&gt;Zeitschrift für Physik, C: Particles and Fields&lt;/em&gt;, 37(4), p 617-622.</harvard1>
<ama>Karsch F, Mehr MT, Satz H. Color screening and deconfinement for bound states of heavy quarks. &lt;em&gt;Zeitschrift für Physik, C: Particles and Fields&lt;/em&gt;. 1988;37(4):617-622.</ama>
<dgps>&lt;div style=&quot;text-indent:-25px; padding-left:25px;padding-bottom:0px;&quot;&gt;Karsch, F., Mehr, M.T. &amp;amp; Satz, H. (1988). Color screening and deconfinement for bound states of heavy quarks. &lt;em&gt;Zeitschrift für Physik, C: Particles and Fields&lt;/em&gt;, &lt;em&gt;37&lt;/em&gt;(4), 617-622. doi:10.1007/BF01549722.&lt;/div&gt;</dgps>
</bibliographicCitation>
</extension>
<recordInfo><recordIdentifier>1784493</recordIdentifier><recordChangeDate encoding="w3cdtf">2012-01-26T08:38:18Z</recordChangeDate>
</recordInfo>
</mods>
</recordData><recordPosition>1</recordPosition></record>
</records>

<extraResponseData></extraResponseData> 
<echoedSearchRetrieveRequest><version>1.1</version><query>id=1784493</query><xQuery><searchClause xmlns="http://www.loc.gov/zing/cql/xcql/"><index>id</index><relation><value>=</value></relation><term>1784493</term></searchClause></xQuery></echoedSearchRetrieveRequest>
</searchRetrieveResponse>
